QueueQ.py
queueq-1.1.0.dist-info/WHEEL
queueq-1.1.0.dist-info/METADATA
queueq-1.1.0.dist-info/RECORD
