Metadata-Version: 2.1
Name: queueq
Version: 1.1.0
Summary: Queue(*elements)
Author: semenchuk Community
Author-email: hootuk@yandex.ru
Requires-Python: >=3.0,<4.0
Classifier: Programming Language :: Python :: 3
Classifier: Programming Language :: Python :: 3.4
Classifier: Programming Language :: Python :: 3.5
Classifier: Programming Language :: Python :: 3.6
Classifier: Programming Language :: Python :: 3.7
Classifier: Programming Language :: Python :: 3.8
Classifier: Programming Language :: Python :: 3.9
